foocat/__init__.py
foocat/foocat.py
foocat-0.1.0.dist-info/LICENSE
foocat-0.1.0.dist-info/WHEEL
foocat-0.1.0.dist-info/METADATA
foocat-0.1.0.dist-info/RECORD
