Metadata-Version: 2.1
Name: foocat
Version: 0.1.0
Summary: Python package that eases the pain concatenating Pandas categoricals!
License: MIT
Author: Mike Chen
Author-email: mike_T_Chen@hotmail.com
Requires-Python: >=3.7,<4.0
Classifier: License :: OSI Approved :: MIT License
Classifier: Programming Language :: Python :: 3
Classifier: Programming Language :: Python :: 3.7
Classifier: Programming Language :: Python :: 3.8
Requires-Dist: pandas (>=1.0.1,<2.0.0)
